ALU/Alu_8.v
`timescale 1ns / 1ps
//////////////////////////////////////////////////////////////////////////////////
// Company: 
// Engineer: 
// 
// Create Date: 03/27/2023 07:27:49 PM
// Design Name: 
// Module Name: Alu_8
// Project Name: 
// Target Devices: 
// Tool Versions: 
// Description: 
// 
// Dependencies: 
// 
// Revision:
// Revision 0.01 - File Created
// Additional Comments:
// 
//////////////////////////////////////////////////////////////////////////////////


module Alu_8(   input[7:0] a,
                input[7:0] b,
                output reg [7:0]  out,
                output reg cout,	
                input aluOp
    );
    
      
 //Always
  always @ (a or b or aluOp) begin
    
    //if op[1] & 1
    if (aluOp == 1'b1) begin
      
      //sll(a,b,c)
      {cout,out} = a << b;
      
    //else if op[0] & 1
    end else begin
  
      //out = a + b
      {cout,out} = a + b;
    end
    
   
  end
//add(a,b,c)
endmodule

ALU/Alu_8_tb.v
`timescale 1ns / 1ps
//////////////////////////////////////////////////////////////////////////////////
// Company: 
// Engineer: 
// 
// Create Date: 03/27/2023 07:29:05 PM
// Design Name: 
// Module Name: Alu_8_tb
// Project Name: 
// Target Devices: 
// Tool Versions: 
// Description: 
// 
// Dependencies: 
// 
// Revision:
// Revision 0.01 - File Created
// Additional Comments:
// 
//////////////////////////////////////////////////////////////////////////////////
// Code your testbench here
// or browse Examples
module alu_8_tb;
  reg [7:0] a;
  reg [7:0] b;
  reg aluOp;
  wire [7:0] out;
  wire _;
  reg i;
  
  Alu_8 alu(.a(a),
        .b(b),
        .out(out),
        .cout(_),
        .aluOp(aluOp));
  
  initial begin 
    a = 0;
    b = 0;
    aluOp = 0;
    $monitor ("a=%d b=%d aluOp=%d out=%d",a,b,aluOp,out);
    
  end
   
  //Testing  Alu add
  initial begin
    aluOp =0;
    for (i = 0; i < 10; i = i+1) begin
      #10 a =$urandom%100;
      	  b = $urandom%100;
    end
  end
    
  //Testing Alu sll
  initial begin
    aluOp = 1;
    for (i = 0; i < 10; i = i+1) begin
      #10 a =$urandom%50;
      	  b = $urandom%5;
    end
  end
  
  
    
    initial begin
      $dumpvars;
      $dumpfile("dump.vcd");
    end
     
endmodule

CSE490-Project1.sim/sim_1/behav/xsim/dump.vcd
$date
   Wed Mar 29 15:44:52 2023
$end
$version
  2019.2
$end
$timescale
  1ps
$end
$scope module alu_8_tb $end
$var reg 8 ! a [7:0] $end
$var reg 8 " b [7:0] $end
$var reg 1 # aluOp $end
$var wire 8 $ out [7:0] $end
$var wire 1 % _ $end
$var reg 1 & i $end
$scope module alu $end
$var wire 8 ' a [7:0] $end
$var wire 8 ( b [7:0] $end
$var reg 8 ) out [7:0] $end
$var reg 1 * cout $end
$var wire 1 + aluOp $end
$upscope $end
$upscope $end
$enddefinitions $end
#0
$dumpvars
b0 !
b0 "
1#
b0 $
0%
0&
b0 '
b0 (
b0 )
0*
1+
$end
#10000
b1101 !
b100 "
b11010000 $
0&
b1101 '
b100 (
b11010000 )
0*
#20000
b1100 !
b10 "
b110000 $
0&
b1100 '
b10 (
b110000 )
0*
#30000
b11110 !
b0 "
b11110 $
0&
b11110 '
b0 (
b11110 )
0*
#40000
b101010 !
b11 "
b1010000 $
1%
0&
b101010 '
b11 (
b1010000 )
1*
#50000
b11110 !
b1 "
b111100 $
0%
0&
b11110 '
b1 (
b111100 )
0*
#60000
b101111 !
b10 "
b10111100 $
0&
b101111 '
b10 (
b10111100 )
0*
#70000
b11011 !
b0 "
b11011 $
0&
b11011 '
b0 (
b11011 )
0*
#80000
b110 !
b100 "
b1100000 $
0&
b110 '
b100 (
b1100000 )
0*
#90000
b110000 !
b10 "
b11000000 $
0&
b110000 '
b10 (
b11000000 )
0*
#100000
b10111 !
b10 "
b1011100 $
0&
b10111 '
b10 (
b1011100 )
0*
#110000
b110001 !
b1 "
b1100010 $
0&
b110001 '
b1 (
b1100010 )
0*
#120000
b100110 !
b11 "
b110000 $
1%
0&
b100110 '
b11 (
b110000 )
1*
#130000
b100111 !
b10 "
b10011100 $
0%
0&
b100111 '
b10 (
b10011100 )
0*
#140000
b11011 !
b0 "
b11011 $
0&
b11011 '
b0 (
b11011 )
0*
#150000
b101101 !
b1 "
b1011010 $
0&
b101101 '
b1 (
b1011010 )
0*
#160000
b101000 !
b1 "
b1010000 $
0&
b101000 '
b1 (
b1010000 )
0*
#170000
b11110 !
b11 "
b11110000 $
0&
b11110 '
b11 (
b11110000 )
0*
#180000
b11001 !
b100 "
b10010000 $
1%
0&
b11001 '
b100 (
b10010000 )
1*
#190000
b100100 !
b10 "
0%
0&
b100100 '
b10 (
b10010000 )
0*
#200000
b1110 !
b0 "
b1110 $
0&
b1110 '
b0 (
b1110 )
0*
#210000
b100101 !
b1 "
b1001010 $
0&
b100101 '
b1 (
b1001010 )
0*
#220000
b110001 !
b0 "
b110001 $
0&
b110001 '
b0 (
b110001 )
0*
#230000
b1010 !
b0 "
b1010 $
0&
b1010 '
b0 (
b1010 )
0*
#240000
b101101 !
b11 "
b1101000 $
1%
0&
b101101 '
b11 (
b1101000 )
1*
#250000
b1010 !
b10 "
b101000 $
0%
0&
b1010 '
b10 (
b101000 )
0*
#260000
b11001 !
b1 "
b110010 $
0&
b11001 '
b1 (
b110010 )
0*
#270000
b1110 !
b1 "
b11100 $
0&
b1110 '
b1 (
b11100 )
0*
#280000
b10101 !
b0 "
b10101 $
0&
b10101 '
b0 (
b10101 )
0*
#290000
b10100 !
b11 "
b10100000 $
0&
b10100 '
b11 (
b10100000 )
0*
#300000
b110000 !
b1 "
b1100000 $
0&
b110000 '
b1 (
b1100000 )
0*
#310000
b10101 !
b1 "
b101010 $
0&
b10101 '
b1 (
b101010 )
0*
#320000
b1101 !
b11 "
b1101000 $
0&
b1101 '
b11 (
b1101000 )
0*
#330000
b10101 !
b1 "
b101010 $
0&
b10101 '
b1 (
b101010 )
0*
#340000
b11110 !
b11 "
b11110000 $
0&
b11110 '
b11 (
b11110000 )
0*
#350000
b100010 !
b0 "
b100010 $
0&
b100010 '
b0 (
b100010 )
0*
#360000
b100110 !
b1 "
b1001100 $
0&
b100110 '
b1 (
b1001100 )
0*
#370000
b111 !
b0 "
b111 $
0&
b111 '
b0 (
b111 )
0*
#380000
b1 !
b0 "
b1 $
0&
b1 '
b0 (
b1 )
0*
#390000
b10000 !
b1 "
b100000 $
0&
b10000 '
b1 (
b100000 )
0*
#400000
b11 !
b10 "
b1100 $
0&
b11 '
b10 (
b1100 )
0*
#410000
b1100 !
b100 "
b11000000 $
0&
b1100 '
b100 (
b11000000 )
0*
#420000
b10110 !
b0 "
b10110 $
0&
b10110 '
b0 (
b10110 )
0*
#430000
b101110 !
b1 "
b1011100 $
0&
b101110 '
b1 (
b1011100 )
0*
#440000
b1001 !
b0 "
b1001 $
0&
b1001 '
b0 (
b1001 )
0*
#450000
b100000 !
b11 "
b0 $
1%
0&
b100000 '
b11 (
b0 )
1*
#460000
b101010 !
b0 "
b101010 $
0%
0&
b101010 '
b0 (
b101010 )
0*
#470000
b1011 !
b11 "
b1011000 $
0&
b1011 '
b11 (
b1011000 )
0*
#480000
b101010 !
b100 "
b10100000 $
0&
b101010 '
b100 (
b10100000 )
0*
#490000
b100110 !
b1 "
b1001100 $
0&
b100110 '
b1 (
b1001100 )
0*
#500000
b11010 !
b11 "
b11010000 $
0&
b11010 '
b11 (
b11010000 )
0*
#510000
b101001 !
b10 "
b10100100 $
0&
b101001 '
b10 (
b10100100 )
0*
#520000
b101100 !
b11 "
b1100000 $
1%
0&
b101100 '
b11 (
b1100000 )
1*
#530000
b101 !
b10 "
b10100 $
0%
0&
b101 '
b10 (
b10100 )
0*
#540000
b11110 !
b10 "
b1111000 $
0&
b11110 '
b10 (
b1111000 )
0*
#550000
b101001 !
b1 "
b1010010 $
0&
b101001 '
b1 (
b1010010 )
0*
#560000
b11011 !
b10 "
b1101100 $
0&
b11011 '
b10 (
b1101100 )
0*
#570000
b0 !
b100 "
b0 $
0&
b0 '
b100 (
b0 )
0*
#580000
b101110 !
b10 "
b10111000 $
0&
b101110 '
b10 (
b10111000 )
0*
#590000
b100101 !
b10 "
b10010100 $
0&
b100101 '
b10 (
b10010100 )
0*
#600000
b101011 !
b100 "
b10110000 $
0&
b101011 '
b100 (
b10110000 )
0*
#610000
b100110 !
b1 "
b1001100 $
0&
b100110 '
b1 (
b1001100 )
0*
#620000
b100001 !
b10 "
b10000100 $
0&
b100001 '
b10 (
b10000100 )
0*
#630000
b10010 !
b1 "
b100100 $
0&
b10010 '
b1 (
b100100 )
0*
#640000
b10010 !
b11 "
b10010000 $
0&
b10010 '
b11 (
b10010000 )
0*
#650000
b10011 !
b10 "
b1001100 $
0&
b10011 '
b10 (
b1001100 )
0*
#660000
b100101 !
b1 "
b1001010 $
0&
b100101 '
b1 (
b1001010 )
0*
#670000
b11110 !
b0 "
b11110 $
0&
b11110 '
b0 (
b11110 )
0*
#680000
b1 !
b0 "
b1 $
0&
b1 '
b0 (
b1 )
0*
#690000
b1001 !
b0 "
b1001 $
0&
b1001 '
b0 (
b1001 )
0*
#700000
b101011 !
b0 "
b101011 $
0&
b101011 '
b0 (
b101011 )
0*
#710000
b101110 !
b0 "
b101110 $
0&
b101110 '
b0 (
b101110 )
0*
#720000
b101010 !
b10 "
b10101000 $
0&
b101010 '
b10 (
b10101000 )
0*
#730000
b100101 !
b10 "
b10010100 $
0&
b100101 '
b10 (
b10010100 )
0*
#740000
b110001 !
b0 "
b110001 $
0&
b110001 '
b0 (
b110001 )
0*
#750000
b100100 !
b11 "
b100000 $
1%
0&
b100100 '
b11 (
b100000 )
1*
#760000
b101011 !
b100 "
b10110000 $
0%
0&
b101011 '
b100 (
b10110000 )
0*
#770000
b100001 !
b100 "
b10000 $
0&
b100001 '
b100 (
b10000 )
0*
#780000
b1011 !
b1 "
b10110 $
0&
b1011 '
b1 (
b10110 )
0*
#790000
b101000 !
b1 "
b1010000 $
0&
b101000 '
b1 (
b1010000 )
0*
#800000
b101101 !
b0 "
b101101 $
0&
b101101 '
b0 (
b101101 )
0*
#810000
b11 !
b10 "
b1100 $
0&
b11 '
b10 (
b1100 )
0*
#820000
b101110 !
b11 "
b1110000 $
1%
0&
b101110 '
b11 (
b1110000 )
1*
#830000
b1111 !
b10 "
b111100 $
0%
0&
b1111 '
b10 (
b111100 )
0*
#840000
b10100 !
b0 "
b10100 $
0&
b10100 '
b0 (
b10100 )
0*
#850000
b1 !
b11 "
b1000 $
0&
b1 '
b11 (
b1000 )
0*
#860000
b1111 !
b11 "
b1111000 $
0&
b1111 '
b11 (
b1111000 )
0*
#870000
b1100 !
b10 "
b110000 $
0&
b1100 '
b10 (
b110000 )
0*
#880000
b100111 !
b10 "
b10011100 $
0&
b100111 '
b10 (
b10011100 )
0*
#890000
b110 !
b1 "
b1100 $
0&
b110 '
b1 (
b1100 )
0*
#900000
b100100 !
b10 "
b10010000 $
0&
b100100 '
b10 (
b10010000 )
0*
#910000
b101100 !
b10 "
b10110000 $
0&
b101100 '
b10 (
b10110000 )
0*
#920000
b100110 !
b10 "
b10011000 $
0&
b100110 '
b10 (
b10011000 )
0*
#930000
b100101 !
b11 "
b101000 $
1%
0&
b100101 '
b11 (
b101000 )
1*
#940000
b11010 !
b11 "
b11010000 $
0%
0&
b11010 '
b11 (
b11010000 )
0*
#950000
b111 !
b11 "
b111000 $
0&
b111 '
b11 (
b111000 )
0*
#960000
b100101 !
b1 "
b1001010 $
0&
b100101 '
b1 (
b1001010 )
0*
#970000
b101110 !
b1 "
b1011100 $
0&
b101110 '
b1 (
b1011100 )
0*
#980000
b11110 !
b0 "
b11110 $
0&
b11110 '
b0 (
b11110 )
0*
#990000
b100010 !
b100 "
b100000 $
0&
b100010 '
b100 (
b100000 )
0*
#1000000
b10 !
b1 "
b100 $
0&
b10 '
b1 (
b100 )
0*
