CSE490-Project1.srcs/sources_1/new/program_counter.v
`timescale 1ns / 1ps
//////////////////////////////////////////////////////////////////////////////////
// Company: 
// Engineer: 
// 
// Create Date: 03/29/2023 02:46:41 PM
// Design Name: 
// Module Name: program_counter
// Project Name: 
// Target Devices: 
// Tool Versions: 
// Description: 
// 
// Dependencies: 
// 
// Revision:
// Revision 0.01 - File Created
// Additional Comments:
// 
//////////////////////////////////////////////////////////////////////////////////


module program_counter(
    input [7:0] instructionAddress,
    output [7:0] currentInstructionAddress
    );
    
  reg [7:0] currentInstructionAddress;
  
  always @(instructionAddress)
    begin
      	assign currentInstructionAddress = instructionAddress;
    end
endmodule

CSE490-Project1.srcs/sources_1/new/program_counter_tb.v
`timescale 1ns / 1ps
//////////////////////////////////////////////////////////////////////////////////
// Company: 
// Engineer: 
// 
// Create Date: 03/29/2023 02:51:32 PM
// Design Name: 
// Module Name: program_counter_tb
// Project Name: 
// Target Devices: 
// Tool Versions: 
// Description: 
// 
// Dependencies: 
// 
// Revision:
// Revision 0.01 - File Created
// Additional Comments:
// 
//////////////////////////////////////////////////////////////////////////////////


module program_counter_tb(

    );
    
    reg [7:0]instructionAddress;
   wire [7:0]currentInstructionAddress,nextInputInstructionAddress;
  
  program_counter instName(.instructionAddress(instructionAddress),.currentInstructionAddress(currentInstructionAddress));
  
  initial
    begin
      instructionAddress = 00000000;
    end
  
  always 
    begin
      
      #5 instructionAddress = 1;
      #5 instructionAddress = 2;
      #5 instructionAddress = 3;
      #5 instructionAddress = 4;
      #5 instructionAddress = 5;
      #5 instructionAddress = 6;
      #5 instructionAddress = 7;

    end
  
   initial
    begin
      //create file
      $dumpfile("program_counter.vcd");
      //associate dumping the variables
      $dumpvars;
    end
  
  initial
    begin
      $display("InputAddress\tCurrentAddress");
      $monitor("%b\t%b",instructionAddress,currentInstructionAddress);
    end  
  
      //make sure it ends
initial #200 $finish; 
  //begin is a special keyword 
  //initial is too! 
  // #100 is a time description 
  //how long to observe the signals
  //$finish this is a directive 
  //what this does: after 100 time units stop
  //in the future there is only one thing to change
  //the time value


//close module
endmodule

CSE490-Project1.sim/sim_1/behav/xsim/program_counter.vcd
$date
   Wed Mar 29 15:50:01 2023
$end
$version
  2019.2
$end
$timescale
  1ps
$end
$scope module program_counter_tb $end
$var reg 8 ! instructionAddress [7:0] $end
$var wire 8 " currentInstructionAddress [7:0] $end
$var wire 8 # nextInputInstructionAddress [7:0] $end
$scope module instName $end
$var wire 8 $ instructionAddress [7:0] $end
$var reg 8 % currentInstructionAddress [7:0] $end
$upscope $end
$upscope $end
$enddefinitions $end
#0
$dumpvars
b0 !
b0 "
bz #
b0 $
b0 %
$end
#5000
b1 !
b1 "
b1 $
b1 %
#10000
b10 !
b10 "
b10 $
b10 %
#15000
b11 !
b11 "
b11 $
b11 %
#20000
b100 !
b100 "
b100 $
b100 %
#25000
b101 !
b101 "
b101 $
b101 %
#30000
b110 !
b110 "
b110 $
b110 %
#35000
b111 !
b111 "
b111 $
b111 %
#40000
b1 !
b1 "
b1 $
b1 %
#45000
b10 !
b10 "
b10 $
b10 %
#50000
b11 !
b11 "
b11 $
b11 %
#55000
b100 !
b100 "
b100 $
b100 %
#60000
b101 !
b101 "
b101 $
b101 %
#65000
b110 !
b110 "
b110 $
b110 %
#70000
b111 !
b111 "
b111 $
b111 %
#75000
b1 !
b1 "
b1 $
b1 %
#80000
b10 !
b10 "
b10 $
b10 %
#85000
b11 !
b11 "
b11 $
b11 %
#90000
b100 !
b100 "
b100 $
b100 %
#95000
b101 !
b101 "
b101 $
b101 %
#100000
b110 !
b110 "
b110 $
b110 %
#105000
b111 !
b111 "
b111 $
b111 %
#110000
b1 !
b1 "
b1 $
b1 %
#115000
b10 !
b10 "
b10 $
b10 %
#120000
b11 !
b11 "
b11 $
b11 %
#125000
b100 !
b100 "
b100 $
b100 %
#130000
b101 !
b101 "
b101 $
b101 %
#135000
b110 !
b110 "
b110 $
b110 %
#140000
b111 !
b111 "
b111 $
b111 %
#145000
b1 !
b1 "
b1 $
b1 %
#150000
b10 !
b10 "
b10 $
b10 %
#155000
b11 !
b11 "
b11 $
b11 %
#160000
b100 !
b100 "
b100 $
b100 %
#165000
b101 !
b101 "
b101 $
b101 %
#170000
b110 !
b110 "
b110 $
b110 %
#175000
b111 !
b111 "
b111 $
b111 %
#180000
b1 !
b1 "
b1 $
b1 %
#185000
b10 !
b10 "
b10 $
b10 %
#190000
b11 !
b11 "
b11 $
b11 %
#195000
b100 !
b100 "
b100 $
b100 %
